{
  "node_id": "math-m-axial-symmetry",
  "topic": "轴对称",
  "name_zh": "轴对称",
  "subject": "math",
  "stage": "middle",
  "curriculum": "cn",
  "lookup_at": "2026-06-02T07:16:36Z",
  "sources": [
    "kp-json",
    "child-kp"
  ],
  "curriculum_excerpts": [
    {
      "id": "cp-1",
      "text": "能理解图形的变化（平移、旋转、轴对称、相似、位似）。",
      "source": "kp-json#curriculum_points"
    },
    {
      "id": "cp-2",
      "text": "图形与几何领域包括图形的性质、图形的变化、图形与坐标三个主题。",
      "source": "kp-json#curriculum_points"
    },
    {
      "id": "curriculum-md-raw",
      "text": "## 图文参考资料\n\n### 轴对称与轴对称图形\n\n---\n\n#### 定义\n\n**轴对称图形**：如果一个图形沿一条直线折叠，直线两旁的部分能够互相重合，这个图形叫做轴对称图形。\n\n**轴对称**：如果两个图形沿一条直线折叠，能够完全重合，这两个图形叫做轴对称。\n\n**要点**：\n- 对称轴是一条直线\n- 轴对称涉及两个图形\n- 轴对称图形是一个图形\n\n---\n\n#### 性质\n\n1. 轴对称图形的对称轴是一条直线\n2. 轴对称的两个图形，对应点连线被对称轴垂直平分\n3. 轴对称的两个图形，对应线段相等，对应角相等\n\n---\n\n#### 常见轴对称图形\n\n| 图形 | 对称轴数量 | 对称轴位置 |\n|:---:|:---:|:---|\n| 线段 | 2条 | 垂直平分线、本身所在直线 |\n| 角 | 1条 | 角平分线所在直线 |\n| 等腰三角形 | 1条 | 底边上的高（或顶角平分线）所在直线 |\n| 矩形 | 2条 | 对边中点连线 |\n| 菱形 | 2条 | 对角线所在直线 |\n| 正方形 | 4条 | 对边中点连线、对角线所在直线 |\n| 圆 | 无数条 | 直径所在直线 |\n\n---\n\n#### 典型例题（基础→综合）\n\n**例1（判断轴对称图形）**\n下列图形中，哪些是轴对称图形？各有几条对称轴？\n(1) 线段  (2) 角  (3) 等腰三角形  (4) 平行四边形\n\n**解**：\n(1) 线段是轴对称图形，有2条对称轴\n(2) 角是轴对称图形，有1条对称轴\n(3) 等腰三角形是轴对称图形，有1条对称轴\n(4) 平行四边形不一定是轴对称图形\n\n---\n\n**例2（求对称点坐标）**\n点 $A(3, 4)$ 关于直线 $x = 1$ 的对称点为 $A'$。求 $A'$ 的坐标。\n\n**解**：\n设 $A'(x, y)$\n$\\because A$ 和 $A'$",
      "source": "kp-json#supplements.curriculum_md_raw"
    },
    {
      "id": "from-math-m-rational-number-cp-1",
      "text": "理解负数的意义；理解有理数的意义，能用数轴上的点表示有理数，能比较有理数的大小。",
      "source": "child-kp#math-m-rational-number"
    },
    {
      "id": "from-math-m-rational-number-cp-2",
      "text": "掌握有理数的加、减、乘、除、乘方及简单的混合运算（以三步以内为主）；理解有理数的运算律，能运用运算律简化运算。",
      "source": "child-kp#math-m-rational-number"
    },
    {
      "id": "from-math-m-rational-number-cp-3",
      "text": "能运用有理数的运算解决简单问题。",
      "source": "child-kp#math-m-rational-number"
    },
    {
      "id": "from-math-m-rational-operations-cp-2",
      "text": "能熟练地对有理数进行加、减、乘、除、乘方及简单的混合运算（以三步以内为主），理解有理数的运算律，能合理运用运算律简化运算。",
      "source": "child-kp#math-m-rational-operations"
    },
    {
      "id": "from-math-m-algebraic-expression-cp-1",
      "text": "理解整式的概念，掌握合并同类项和去括号的法则；能进行简单的整式加减运算。",
      "source": "child-kp#math-m-algebraic-expression"
    }
  ],
  "exercises": [
    {
      "id": "q-cp-1",
      "stem": "依据课标「轴对称」：能理解图形的变化（平移、旋转、轴对称、相似、位似）。 请结合实例说明。",
      "answer": "应答覆盖课标要点，体现掌握与应用。",
      "source": "kp-json#exercises"
    },
    {
      "id": "q-cp-2",
      "stem": "比较说明：图形与几何领域包括图形的性质、图形的变化、图形与坐标三个主题。",
      "answer": "需写出关键概念、过程或方法，避免只背结论。",
      "source": "kp-json#exercises"
    }
  ],
  "common_errors": [
    {
      "id": "err-1",
      "text": "套公式不求理解",
      "source": "kp-json#errors"
    },
    {
      "id": "err-2",
      "text": "忽视定义域、单位与图形条件",
      "source": "kp-json#errors"
    }
  ],
  "prerequisites": [
    "math-m-geometric-figure",
    "math-m-rotation"
  ],
  "extends": [
    "math-m-rotation"
  ],
  "deep_textbook_snippets": [
    {
      "id": "deep-1",
      "text": "standard forms of parabolas with vertex (0, 0) Table 1 and Figure 5 summarize the standard features of parabolas with a vertex at the origin. Axis of Symmetry Equation Focus Directrix Endpoints of Latus Rectum x-axis y 2 = 4px (p, 0) x = −p (p, ± 2p) y-axis x 2 = 4py (0, p) y = −p (± 2p, p) Table 1 Figure 5 (a) When p > 0 and the axis of symmetry is the x-axis, the parabola opens right. (b) When p < 0 and the axis of symmetry is the x-axis, the parabola opens left. (c) When p < 0 and the axis of symmetry is the y-axis, the parabola opens up. (d) When p < 0 and the axis of symmetry is the y-axis, the parabola opens down. (0, 0) (0, 0) (p, 0) (p, 0) (p, −|2p|) (p, −|2p|) (p, |2p|) (p, |2p|) y y x x (a) (c) (d) (b) x = −p x = −p y ˜ = 4px y ˜ = 4px p > 0 p < 0 (0, 0) (0, 0) (0, p) (0, p) (−|2p|, p) (−|2p|, p) (|2p|, p) (|2p|, p) y y x x y = −p y = −p x˜ = 4py p > 0 x˜ = 4py p < 0 The key features of a parabola are its vertex, axis of symmetry, focus, directrix, and latus rectum. See Figure 5. When given a standard equation for a parabola centered at the origin, we can easily identify the key features to graph the parabola. A line is said to be tangent to a curve if it intersects the curve at exactly one point. If we sketch lines tangent to the parabola at the endpoints of the latus rectum, these lines intersect on the axis of symmetry, as shown in Figure 6. Figure 6 (0, 0) (6, 0) (6, 12) (6, −12) x = −6 y ˜ = 24x y x",
      "source": "books/math/OpenStax_CollegeAlgebra.md",
      "source_type": "local_textbook_markdown",
      "score": "31",
      "match_terms": "symmetry"
    },
    {
      "id": "deep-2",
      "text": "Try It #1 Graph y 2 = −16x. Identify and label the focus, directrix, and endpoints of the latus rectum. Example 2 Graphing a Parabola with Vertex (0, 0) and the y-axis as the Axis of Symmetry Graph x 2 = −6y. Identify and label the focus, directrix, and endpoints of the latus rectum. Solution The standard form that applies to the given equation is x 2 = 4py. Thus, the axis of symmetry is the y-axis. It follows that: • −6 = 4p, so p = −​ 3 __ 2 ​ Since p < 0, the parabola opens down. • the coordinates of the focus are (0, p) = ​ 0, − ​ 3 __ 2 ​  ​ • the equation of the directrix is y = − p = ​ 3 __ 2 ​ • the endpoints of the latus rectum can be found by substituting y = ​ 3 __ 2 ​ into the original equation, ​ ±3, − ​ 3 __ 2 ​  ​ Next we plot the focus, directrix, and latus rectum, and draw a smooth curve to form the parabola. Figure 8 Try It #2 Graph x 2 = 8y. Identify and label the focus, directrix, and endpoints of the latus rectum. Writing Equations of Parabolas in Standard Form In the previous examples, we used the standard form equation of a parabola to calculate the locations of its key features. We can also use the calculations in reverse to write an equation for a parabola when given its key features. How To… Given its focus and directrix, write the equation for a parabola in standard form. 1. Determine whether the axis of symmetry is the x- or y-axis. a. If the given coordinates of the focus have the form (p, 0), then the axis of symmetry is the x-axis.\nUse the standard form y 2 = 4px. b. If the given coordinates of the focus have the form (0, p), then the axis",
      "source": "books/math/OpenStax_CollegeAlgebra.md",
      "source_type": "local_textbook_markdown",
      "score": "30",
      "match_terms": "symmetry"
    },
    {
      "id": "deep-3",
      "text": "(x − 4)2 = 4 ⋅ 7 ⋅ (y + 8) It follows that: • the vertex is (h, k) = (4, −8) • the axis of symmetry is x = h = 4 • since p = 7, p > 0 and so the parabola opens up • the coordinates of the focus are (h, k + p) = (4, −8 + 7) = (4, −1) • the equation of the directrix is y = k − p = −8 − 7 = −15 • the endpoints of the latus rectum are (h ± 2p, k + p) = (4 ± 2(7), −8 + 7), or (−10, −1) and (18, −1) Next we plot the vertex, axis of symmetry, focus, directrix, and latus rectum, and draw a smooth curve to form the parabola. See Figure 11. Figure 11 Try It #5 Graph (x + 2)2 = −20 (y − 3). Identify and label the vertex, axis of symmetry, focus, directrix, and endpoints of the latus rectum. Solving Applied Problems Involving Parabolas As we mentioned at the beginning of the section, parabolas are used to design many objects we use every day, such as telescopes, suspension bridges, microphones, and radar equipment. Parabolic mirrors, such as the one used to light the Olympic torch, have a very unique reflecting property. When rays of light parallel to the parabola’s axis of symmetry are directed toward any surface of the mirror, the light is reflected directly to the focus. See Figure 12. This is why the Olympic torch is ignited when it is held at the focus of the parabolic mirror. (x − 4)2 = 28(y + 8) (4, −1) (18, −1) (4, −8) (−10, −1) y = −15 x = 4 y x",
      "source": "books/math/OpenStax_CollegeAlgebra.md",
      "source_type": "local_textbook_markdown",
      "score": "27",
      "match_terms": "symmetry"
    },
    {
      "id": "deep-4",
      "text": "_______________ 2a ​, to solve ax 2 + bx + c = 0 for the x-intercepts, or zeros, we find the value of x halfway between them is always x = − ​ b __ 2a ​, the equation for the axis of symmetry. Figure 4 represents the graph of the quadratic function written in general form as y = x2 + 4x + 3. In this form, a = 1, b = 4, and c = 3. Because a > 0, the parabola opens upward. The axis of symmetry is x = −​ 4 ____ 2(1) ​ = −2. This also makes sense because we can see from the graph that the vertical line x = −2 divides the graph in half. The vertex always occurs along the axis of symmetry. For a parabola that opens upward, the vertex occurs at the lowest point on the graph, in this instance, (−2, −1). The x-intercepts, those points where the parabola crosses the x-axis, occur at (−3, 0) and (−1, 0). –6 –4\nTh standard form of a quadratic function presents the function in the form f(x) = a(x − h)2 + k where (h, k) is the vertex. Because the vertex appears in the standard form of the quadratic function, this form is also known as the vertex form of a quadratic function. As with the general form, if a > 0, the parabola opens upward and the vertex is a minimum. If a < 0, the parabola opens downward, and the vertex is a maximum. Figure 5 represents the graph of the quadratic function written in standard form as y = −3(x + 2)2 + 4. Since x − h = x + 2 in this example, h = −2. In this form, a = −3, h = −2, and k = 4. Because a < 0, the parabola opens downward. The vertex is at (−2, 4). –2 –6 –4 –2\nx y y = −3(x + 2)2 + 4 Vertex Figure 5 The standard form is useful for determining how the",
      "source": "books/math/OpenStax_CollegeAlgebra.md",
      "source_type": "local_textbook_markdown",
      "score": "25",
      "match_terms": "symmetry"
    }
  ],
  "textbook_refs": [
    {
      "book": "deep_textbook_snippet",
      "chapter": "",
      "path": "books/math/OpenStax_CollegeAlgebra.md",
      "note": "standard forms of parabolas with vertex (0, 0) Table 1 and Figure 5 summarize the standard features of parabolas with a vertex at the origin. Axis of Symmetry Equation Focus Directrix Endpoints of Latus Rectum x-axis y 2 = 4px (p, 0) x = −p (p, ± 2p) y-axis x 2 = 4py (0, p) y = −p (± 2p, p) Table 1 Figure 5 (a) When p > 0 and the axis of symmetry is the x-axis, the parabola opens right. (b) When p < 0 and the axis of symmetry is the x-axis, the parabola opens left. (c) When p < 0 and the axis of symmetry is the y-axis, the parabola opens up. (d) When p < 0 and the axis of symmetry is the y-axi",
      "source": "kp-json#supplements.deep_textbook_snippets"
    },
    {
      "book": "deep_textbook_snippet",
      "chapter": "",
      "path": "books/math/OpenStax_CollegeAlgebra.md",
      "note": "Try It #1 Graph y 2 = −16x. Identify and label the focus, directrix, and endpoints of the latus rectum. Example 2 Graphing a Parabola with Vertex (0, 0) and the y-axis as the Axis of Symmetry Graph x 2 = −6y. Identify and label the focus, directrix, and endpoints of the latus rectum. Solution The standard form that applies to the given equation is x 2 = 4py. Thus, the axis of symmetry is the y-axis. It follows that: • −6 = 4p, so p = −​ 3 __ 2 ​ Since p < 0, the parabola opens down. • the coordinates of the focus are (0, p) = ​ 0, − ​ 3 __ 2 ​  ​ • the equation of the directrix is y = − p = ",
      "source": "kp-json#supplements.deep_textbook_snippets"
    },
    {
      "book": "deep_textbook_snippet",
      "chapter": "",
      "path": "books/math/OpenStax_CollegeAlgebra.md",
      "note": "(x − 4)2 = 4 ⋅ 7 ⋅ (y + 8) It follows that: • the vertex is (h, k) = (4, −8) • the axis of symmetry is x = h = 4 • since p = 7, p > 0 and so the parabola opens up • the coordinates of the focus are (h, k + p) = (4, −8 + 7) = (4, −1) • the equation of the directrix is y = k − p = −8 − 7 = −15 • the endpoints of the latus rectum are (h ± 2p, k + p) = (4 ± 2(7), −8 + 7), or (−10, −1) and (18, −1) Next we plot the vertex, axis of symmetry, focus, directrix, and latus rectum, and draw a smooth curve to form the parabola. See Figure 11. Figure 11 Try It #5 Graph (x + 2)2 = −20 (y − 3). Identify and ",
      "source": "kp-json#supplements.deep_textbook_snippets"
    },
    {
      "book": "deep_textbook_snippet",
      "chapter": "",
      "path": "books/math/OpenStax_CollegeAlgebra.md",
      "note": "_______________ 2a ​, to solve ax 2 + bx + c = 0 for the x-intercepts, or zeros, we find the value of x halfway between them is always x = − ​ b __ 2a ​, the equation for the axis of symmetry. Figure 4 represents the graph of the quadratic function written in general form as y = x2 + 4x + 3. In this form, a = 1, b = 4, and c = 3. Because a > 0, the parabola opens upward. The axis of symmetry is x = −​ 4 ____ 2(1) ​ = −2. This also makes sense because we can see from the graph that the vertical line x = −2 divides the graph in half. The vertex always occurs along the axis of symmetry. For a par",
      "source": "kp-json#supplements.deep_textbook_snippets"
    },
    {
      "book": "textbook_summary",
      "chapter": "",
      "path": "",
      "note": "## 图文参考资料\n\n### 轴对称与轴对称图形\n\n---\n\n#### 定义\n\n**轴对称图形**：如果一个图形沿一条直线折叠，直线两旁的部分能够互相重合，这个图形叫做轴对称图形。\n\n**轴对称**：如果两个图形沿一条直线折叠，能够完全重合，这两个图形叫做轴对称。\n\n**要点**：\n- 对称轴是一条直线\n- 轴对称涉及两个图形\n- 轴对称图形是一个图形\n\n---\n\n#### 性质\n\n1. 轴对称图形的对称轴是一条直线\n2. 轴对称的两个图形，对应点连线被对称轴垂直平分\n3. 轴对称的两个图形，对应线段相等，对应角相等\n\n---\n\n#### 常见轴对称图形\n\n| 图形 | 对称轴数量 | 对称轴位置 |\n|:---:|:---:|:---|\n| 线段 | 2条 | 垂直平分线、本身所在直线 |\n| 角 | 1条 | 角平分线所在直线 |\n| 等腰三角形 | 1条 | 底边上的高（或顶角平分线）所在直线 |\n| 矩形 | 2条 | 对边中点连线 |\n| 菱形 | 2条 | 对角线所在直线 |\n| 正方形 | 4条 | 对边中点连线、对角线所在直线 |\n| 圆 | 无数条 | 直径所在直线 |\n\n---\n\n#### 典型例题（基础→综合）\n\n**例1（判断轴对称图形）**\n下列图形中，哪些是轴对称图形？各有几条对称轴？\n(1) 线段  (2) 角  (3) 等腰三角形  (4) 平行四边",
      "source": "kp-json#textbook_summary"
    }
  ],
  "md_path": null,
  "kp_json_path": "data/kp/math/math-m-axial-symmetry.json",
  "fallback_used": false,
  "gaps": []
}
