{
  "kp_id": "math-cam-igcse-simultaneous-igcse",
  "name": "二元方程组",
  "name_en": "Simultaneous eqs",
  "subject": "math",
  "subject_name": null,
  "curriculum": "cambridge",
  "stage": "igcse",
  "grade": 10,
  "domain_id": "",
  "domain_name": "代数与图像 / Algebra & Graphs / Algebra & Graphs",
  "tree_file": "data/trees/cambridge/igcse/math.json",
  "curriculum_points": [
    "C6.1 Pythagoras’ theorem Notes and examples\nKnow and use Pythagoras’ theorem.",
    "C6.2 Right-angled triangles\n1 Know and use the sine, cosine and tangent ratios for acute angles in calculations involving sides and angles of a right-angled triangle.",
    "C6.2 Right-angled triangles\n2 Solve problems in two dimensions using Pythagoras’ theorem and trigonometry."
  ],
  "difficulty": 3,
  "interactive_resources": [],
  "textbook_content": {},
  "supplements": {},
  "errors": [],
  "exercises": [],
  "memory_anchors": [],
  "real_world": [],
  "bloom_verbs": {},
  "notes": [],
  "_meta": {
    "schema_version": "1.0",
    "generated_at": "2026-06-17T13:05:18.929252+00:00",
    "sources": [
      "tree"
    ],
    "excerpt_count": 0
  }
}