{
  "node_id": "math-m-quadratic-equation",
  "topic": "一元二次方程",
  "name_zh": "一元二次方程",
  "subject": "math",
  "stage": "middle",
  "curriculum": "cn",
  "lookup_at": "2026-06-02T07:16:39Z",
  "sources": [
    "kp-json"
  ],
  "curriculum_excerpts": [
    {
      "id": "cp-1",
      "text": "理解配方法，能用配方法、公式法、因式分解法解数字系数的一元二次方程。",
      "source": "kp-json#curriculum_points"
    },
    {
      "id": "cp-2",
      "text": "会用一元二次方程根的判别式判别方程是否有实根及两个实根是否相等。",
      "source": "kp-json#curriculum_points"
    },
    {
      "id": "cp-3",
      "text": "能根据一元二次方程的特征，选择配方法、公式法、因式分解法解数字系数的一元二次方程。",
      "source": "kp-json#curriculum_points"
    },
    {
      "id": "cp-4",
      "text": "会用一元二次方程根的判别式判别方程是否有实根及两个实根是否相等，会将一元二次方程根的情况与一元二次方程根的判别式相联系。",
      "source": "kp-json#curriculum_points"
    },
    {
      "id": "cn-tg-1",
      "text": "教学时应注重从学生熟悉的生活情境入手，引导学生通过具体操作、观察、归纳等方式理解一元二次方程的概念。注重知识的发生发展过程，帮助学生建立知识之间的联系。",
      "source": "cn-curriculum#教学提示"
    },
    {
      "id": "cn-tg-2",
      "text": "已知方程 x² - 3x + 2 = 0 的两根为 x₁ 和 x₂，验证：",
      "source": "cn-curriculum#教学提示"
    },
    {
      "id": "cn-tg-3",
      "text": "【说明】引导学生通过求解方程，发现根与系数之间的关系，为后续学习韦达定理做准备。",
      "source": "cn-curriculum#教学提示"
    },
    {
      "id": "cn-ar-1",
      "text": "学生能准确描述一元二次方程的相关概念，能进行基本的运算和推理，能解决与一元二次方程相关的实际问题，形成初步的数学思维和素养。",
      "source": "cn-curriculum#学业要求"
    }
  ],
  "exercises": [
    {
      "id": "q-cp-1",
      "stem": "依据课标「一元二次方程」：理解配方法，能用配方法、公式法、因式分解法解数字系数的一元二次方程。 请结合实例说明。",
      "answer": "应答覆盖课标要点，体现掌握与应用。",
      "source": "kp-json#exercises"
    },
    {
      "id": "q-cp-2",
      "stem": "比较说明：会用一元二次方程根的判别式判别方程是否有实根及两个实根是否相等。",
      "answer": "需写出关键概念、过程或方法，避免只背结论。",
      "source": "kp-json#exercises"
    }
  ],
  "common_errors": [
    {
      "id": "err-1",
      "text": "套公式不求理解",
      "source": "kp-json#errors"
    },
    {
      "id": "err-2",
      "text": "忽视定义域、单位与图形条件",
      "source": "kp-json#errors"
    }
  ],
  "prerequisites": [
    "math-m-monomial-multiplication",
    "math-m-quadratic-radical",
    "math-m-algebraic-expression",
    "math-m-quadratic-function"
  ],
  "extends": [
    "math-m-quadratic-function"
  ],
  "deep_textbook_snippets": [
    {
      "id": "deep-1",
      "text": "Learning Objectives In this section you will: • Solve quadratic equations by factoring. • Solve quadratic equations by the square root property. • Solve quadratic equations by completing the square. • Solve quadratic equations by using the quadratic formula. 2.5 Quadratic Equations Figure 1 The computer monitor on the left in Figure 1 is a 23.6-inch model and the one on the right is a 27-inch model. Proportionally, the monitors appear very similar. If there is a limited amount of space and we desire the largest monitor possible, how do we decide which one to choose? In this section, we will learn how to solve problems such as this using four different methods. Solving Quadratic Equations by Factoring An equation containing a second-degree polynomial is called a quadratic equation. For example, equations such as 2x2 + 3x − 1 = 0 and x2 − 4 = 0 are quadratic equations. They are used in countless ways in the fields of engineering, architecture, finance, biological science, and, of course, mathematics. Often the easiest method of solving a quadratic equation is factoring. Factoring means finding expressions that can be multiplied together to give the expression on one side of the equation. If a quadratic equation can be factored, it is written as a product of linear terms. Solving by factoring depends on the zero-product property, which states that if a ⋅ b = 0, then a = 0 or b = 0, where a and b are real numbers or algebraic expressions. In other words, if the product of two numbers or two expressions equals zero, then one of the numbers or one of the expressions must equal ze",
      "source": "books/math/OpenStax_CollegeAlgebra.md",
      "source_type": "local_textbook_markdown",
      "score": "81",
      "match_terms": "quadratic equations, quadratic, equations"
    },
    {
      "id": "deep-2",
      "text": "the zero-product property and quadratic equations Th zero-product property states If a ⋅ b = 0, then a = 0 or b = 0, where a and b are real numbers or algebraic expressions. A quadratic equation is an equation containing a second-degree polynomial; for example ax 2 + bx + c = 0 where a, b, and c are real numbers, and if a ≠ 0, it is in standard form. Solving Quadratics with a Leading Coefficient of 1 In the quadratic equation x2 + x − 6 = 0, the leading coefficient, or the coefficient of x2, is 1. We have one method of factoring quadratic equations in this form. How To… Given a quadratic equation with the leading coefficient of 1, factor it. 1. Find two numbers whose product equals c and whose sum equals b. 2. Use those numbers to write two factors of the form (x + k) or (x − k), where k is one of the numbers found in step 1. Use the numbers exactly as they are. In other words, if the two numbers are 1 and −2, the factors are (x + 1)(x − 2). 3. Solve using the zero-product property by setting each factor equal to zero and solving for the variable. Example 1 Factoring and Solving a Quadratic with Leading Coefficient of 1 Factor and solve the equation: x 2 + x − 6 = 0. Solution To factor x 2 + x − 6 = 0, we look for two numbers whose product equals −6 and whose sum equals 1. Begin by looking at the possible factors of −6. 1 ⋅ (−6) (−6) ⋅ 1 2 ⋅ (−3) 3 ⋅ (−2) The last pair, 3 ⋅ (−2) sums to 1, so these are the numbers. Note that only one pair of numbers will work. Then, write the factors.\n(x − 2)(x + 3) = 0 To solve this equation, we use the zero-product property. Set each fact",
      "source": "books/math/OpenStax_CollegeAlgebra.md",
      "source_type": "local_textbook_markdown",
      "score": "71",
      "match_terms": "quadratic equations, quadratic, equations"
    },
    {
      "id": "deep-3",
      "text": "Solving Equations Using Factoring We have used factoring to solve quadratic equations, but it is a technique that we can use with many types of polynomial equations, which are equations that contain a string of terms including numerical coefficients and variables. When we are faced with an equation containing polynomials of degree higher than 2, we can often solve them by factoring. polynomial equations A polynomial of degree n is an expression of the type anx n + an − 1x n − 1 + ⋅ ⋅ ⋅ + a2x 2 + a1 x + a0 where n is a positive integer and an, … , a0 are real numbers and an ≠ 0. Setting the polynomial equal to zero gives a polynomial equation. The total number of solutions (real and complex) to a polynomial equation is equal to the highest exponent n. Example 4 Solving a Polynomial by Factoring Solve the polynomial by factoring: 5x 4 = 80x 2. Solution First, set the equation equal to zero. Then factor out what is common to both terms, the GCF.\n5x 2(x 2 − 16) = 0 Notice that we have the difference of squares in the factor x 2 − 16, which we will continue to factor and obtain two solutions. The first term, 5x 2, generates, technically, two solutions as the exponent is 2, but they are the same solution.\nx = 4 or x = −4 The solutions are 0 (double solution ), 4, and −4. Analysis We can see the solutions on the graph in Figure 1. The x-coordinates of the points where the graph crosses the x-axis are the solutions—the x-intercepts. Notice on the graph that at 0, the graph touches the x-axis and bounces back. It does not cross the x-axis. This is typical of double solutions. Figure",
      "source": "books/math/OpenStax_CollegeAlgebra.md",
      "source_type": "local_textbook_markdown",
      "score": "59",
      "match_terms": "quadratic equations, quadratic, equations"
    },
    {
      "id": "deep-4",
      "text": "Try It #6 Solve the quadratic equation using the square root property: 3(x − 4)2 = 15. Completing the Square Not all quadratic equations can be factored or can be solved in their original form using the square root property. In these cases, we may use a method for solving a quadratic equation known as completing the square. Using this method, we add or subtract terms to both sides of the equation until we have a perfect square trinomial on one side of the equal sign. We then apply the square root property. To complete the square, the leading coefficient, a, must equal 1. If it does not, then divide the entire equation by a. Then, we can use the following procedures to solve a quadratic equation by completing the square. We will use the example x2 + 4x + 1 = 0 to illustrate each step. 1. Given a quadratic equation that cannot be factored, and with a = 1, fi st add or subtract the constant term to the right sign of the equal sign.\n22 = 4 3. Add ​ ​ 1 _ 2 ​b  ​ 2​ to both sides of the equal sign and simplify the right side. We have\nx 2 + 4x + 4 = 3 4. The left side f the equation can now be factored as a perfect square.\nx = −2 ± ​√ — 3 ​ 6. The solutions are −2 + ​√ — 3 ​ and −2 − ​√ — 3 ​. Example 8 Solving a Quadratic by Completing the Square Solve the quadratic equation by completing the square: x 2 − 3x − 5 = 0. Solution First, move the constant term to the right side of the equal sign.\n​ −​ 3 _ 2 ​  ​ 2​ = ​ 9 _ 4 ​ Add the result to both sides of the equal sign.\nx 2 − 3x + ​ 9 _ 4 ​ = 5 + ​ 9 _ 4 ​ Factor the left ide as a perfect square and simplify the right side.",
      "source": "books/math/OpenStax_CollegeAlgebra.md",
      "source_type": "local_textbook_markdown",
      "score": "58",
      "match_terms": "quadratic equations, quadratic, equations"
    }
  ],
  "textbook_refs": [
    {
      "book": "deep_textbook_snippet",
      "chapter": "",
      "path": "books/math/OpenStax_CollegeAlgebra.md",
      "note": "Learning Objectives In this section you will: • Solve quadratic equations by factoring. • Solve quadratic equations by the square root property. • Solve quadratic equations by completing the square. • Solve quadratic equations by using the quadratic formula. 2.5 Quadratic Equations Figure 1 The computer monitor on the left in Figure 1 is a 23.6-inch model and the one on the right is a 27-inch model. Proportionally, the monitors appear very similar. If there is a limited amount of space and we desire the largest monitor possible, how do we decide which one to choose? In this section, we will le",
      "source": "kp-json#supplements.deep_textbook_snippets"
    },
    {
      "book": "deep_textbook_snippet",
      "chapter": "",
      "path": "books/math/OpenStax_CollegeAlgebra.md",
      "note": "the zero-product property and quadratic equations Th zero-product property states If a ⋅ b = 0, then a = 0 or b = 0, where a and b are real numbers or algebraic expressions. A quadratic equation is an equation containing a second-degree polynomial; for example ax 2 + bx + c = 0 where a, b, and c are real numbers, and if a ≠ 0, it is in standard form. Solving Quadratics with a Leading Coefficient of 1 In the quadratic equation x2 + x − 6 = 0, the leading coefficient, or the coefficient of x2, is 1. We have one method of factoring quadratic equations in this form. How To… Given a quadratic equat",
      "source": "kp-json#supplements.deep_textbook_snippets"
    },
    {
      "book": "deep_textbook_snippet",
      "chapter": "",
      "path": "books/math/OpenStax_CollegeAlgebra.md",
      "note": "Solving Equations Using Factoring We have used factoring to solve quadratic equations, but it is a technique that we can use with many types of polynomial equations, which are equations that contain a string of terms including numerical coefficients and variables. When we are faced with an equation containing polynomials of degree higher than 2, we can often solve them by factoring. polynomial equations A polynomial of degree n is an expression of the type anx n + an − 1x n − 1 + ⋅ ⋅ ⋅ + a2x 2 + a1 x + a0 where n is a positive integer and an, … , a0 are real numbers and an ≠ 0. Setting the pol",
      "source": "kp-json#supplements.deep_textbook_snippets"
    },
    {
      "book": "deep_textbook_snippet",
      "chapter": "",
      "path": "books/math/OpenStax_CollegeAlgebra.md",
      "note": "Try It #6 Solve the quadratic equation using the square root property: 3(x − 4)2 = 15. Completing the Square Not all quadratic equations can be factored or can be solved in their original form using the square root property. In these cases, we may use a method for solving a quadratic equation known as completing the square. Using this method, we add or subtract terms to both sides of the equation until we have a perfect square trinomial on one side of the equal sign. We then apply the square root property. To complete the square, the leading coefficient, a, must equal 1. If it does not, then d",
      "source": "kp-json#supplements.deep_textbook_snippets"
    },
    {
      "book": "textbook_summary",
      "chapter": "",
      "path": "",
      "note": "## 图文参考资料\n\n### 一元二次方程的概念与解法\n\n---\n\n#### 定义\n\n**一元二次方程**是只含有一个未知数，且未知数的最高次数为 $2$ 的整式方程。\n\n**标准形式**：\n$$\\boxed{ax^2 + bx + c = 0 \\quad (a \\neq 0)}$$\n\n**要点**：\n- $a$ 是二次项系数\n- $b$ 是一次项系数\n- $c$ 是常数项\n\n---\n\n#### 解法（四种方法）\n\n**方法一：直接开平方法**\n适用于 $x^2 = p$ 或 $(mx+n)^2 = p$ 形式。\n\n**方法二：配方法**\n将方程化为 $(x+m)^2 = n$ 形式。\n\n**步骤**：\n1. 移项：将常数项移到右边\n2. 化1：二次项系数化为1\n3. 配方：两边加上一次项系数一半的平方\n4. 求解：开平方\n\n**方法三：公式法**\n$$x = \\frac{-b \\pm \\sqrt{b^2-4ac}}{2a}$$\n\n**方法四：因式分解法**\n将方程化为 $a(x-x_1)(x-x_2) = 0$ 形式。\n\n---\n\n#### 根的判别式\n\n$$\\Delta = b^2 - 4ac$$\n\n| $\\Delta$ 的符号 | 根的情况 |\n|:---:|:---|\n| $\\Delta > 0$ | 两个不相等的实数根 |\n| $\\Delta = 0$ | 两个相等的实数",
      "source": "kp-json#textbook_summary"
    }
  ],
  "md_path": null,
  "kp_json_path": "data/kp/math/math-m-quadratic-equation.json",
  "fallback_used": false,
  "gaps": []
}
